README.rst
setup.py
yandex_speech/VERSION.txt
yandex_speech/__init__.py
yandex_speech/nlu.py
yandex_speech/tts.py
yandex_speech.egg-info/PKG-INFO
yandex_speech.egg-info/SOURCES.txt
yandex_speech.egg-info/dependency_links.txt
yandex_speech.egg-info/requires.txt
yandex_speech.egg-info/top_level.txt