Metadata-Version: 1.1
Name: yandex-speech
Version: 0.4
Summary: A library for Yandex speech kit
Home-page: https://github.com/art1415926535/Yandex_speech
Author: Artem Fedotov
Author-email: art1415926535@ya.ru
License: MIT
Keywords: yandex speech kit text-to-speech tts
Platform: UNKNOWN
Classifier: Development Status :: 3 - Alpha
Classifier: Programming Language :: Python :: 2.7
Classifier: Programming Language :: Python :: 3.3
Classifier: Programming Language :: Python :: 3.4
Classifier: Programming Language :: Python :: 3.5
Classifier: Programming Language :: Python :: 3.6
Classifier: Programming Language :: Python :: Implementation :: PyPy
Classifier: Intended Audience :: Developers
Classifier: License :: OSI Approved :: MIT License
Classifier: Natural Language :: Russian
Classifier: Natural Language :: English
Classifier: Natural Language :: Turkish
Classifier: Natural Language :: Ukranian
Classifier: Topic :: Multimedia :: Sound/Audio :: Speech
